LICENSE
pstock/__init__.py
pstock/asset.py
pstock/bar.py
pstock/base.py
pstock/earnings.py
pstock/income_statement.py
pstock/news.py
pstock/quote.py
pstock/trend.py
pstock/types.py
pstock/utils/__init__.py
pstock/utils/chart.py
pstock/utils/financials_quote.py
pstock/utils/quote.py
pstock/utils/utils.py
pstock_python-0.2.0.dist-info/LICENSE
pstock_python-0.2.0.dist-info/WHEEL
pstock_python-0.2.0.dist-info/METADATA
pstock_python-0.2.0.dist-info/RECORD
